aojcli/__init__.py
aojcli/aojcli.py
aojcli/libaoj.py
aojcli-0.8.dist-info/DESCRIPTION.rst
aojcli-0.8.dist-info/METADATA
aojcli-0.8.dist-info/RECORD
aojcli-0.8.dist-info/WHEEL
aojcli-0.8.dist-info/entry_points.txt
aojcli-0.8.dist-info/metadata.json
aojcli-0.8.dist-info/top_level.txt
