Metadata-Version: 2.0
Name: aojcli
Version: 0.8
Summary: AOJ submit tool
Home-page: https://github.com/kamaboko123/aojcli
Author: kamaboko123
Author-email: 6112062+kamaboko123@users.noreply.github.com
License: LGPL
Platform: UNKNOWN
Classifier: Programming Language :: Python :: 3.7
Requires-Dist: requests
Requires-Dist: texttable
